keyring_pass/__init__.py
keyring_pass/__main__.py
keyring_pass-0.9.3.dist-info/LICENSE
keyring_pass-0.9.3.dist-info/METADATA
keyring_pass-0.9.3.dist-info/WHEEL
keyring_pass-0.9.3.dist-info/entry_points.txt
keyring_pass-0.9.3.dist-info/RECORD
