Metadata-Version: 2.1
Name: keyring-pass
Version: 0.9.3
Summary: https://www.passwordstore.org/ backend for https://pypi.org/project/keyring/
Home-page: https://github.com/nazarewk/keyring_pass
License: MIT
Keywords: keyring,pass
Author: Krzysztof Nazarewski
Author-email: 3494992+nazarewk@users.noreply.github.com
Requires-Python: >=3.7
Classifier: License :: OSI Approved :: MIT License
Classifier: Programming Language :: Python :: 3
Classifier: Programming Language :: Python :: 3.7
Classifier: Programming Language :: Python :: 3.8
Classifier: Programming Language :: Python :: 3.9
Classifier: Programming Language :: Python :: 3.10
Classifier: Programming Language :: Python :: 3.11
Classifier: Programming Language :: Python :: 3.12
Requires-Dist: jaraco-classes (>=3.2.3)
Requires-Dist: keyring (>=23.9.3)
Project-URL: Repository, https://github.com/nazarewk/keyring_pass
